S3Upload/__init__.py
S3Upload/s3.py
s3bucketmeu-1.0.1.dist-info/LICENSE.txt
s3bucketmeu-1.0.1.dist-info/METADATA
s3bucketmeu-1.0.1.dist-info/WHEEL
s3bucketmeu-1.0.1.dist-info/top_level.txt
s3bucketmeu-1.0.1.dist-info/RECORD
