Metadata-Version: 2.1
Name: s3bucketmeu
Version: 1.0.1
Summary: projeto exemplo
Home-page: https://github.com/pypa/sampleproject
Author: Example Author
Author-email: antonio.developer10@gmail.com
License: UNKNOWN
Project-URL: Bug Tracker, https://github.com/pypa/sampleproject/issues
Platform: UNKNOWN
Classifier: Programming Language :: Python :: 3
Classifier: License :: OSI Approved :: MIT License
Classifier: Operating System :: OS Independent
Requires-Python: >=3.6
License-File: LICENSE.txt
